setup.py
docs/HISTORY.txt
dupfinder/README.txt
dupfinder/__init__.py
dupfinder/finder.py
dupfinder/manager.py
dupfinder/tests.py
dupfinder.egg-info/PKG-INFO
dupfinder.egg-info/SOURCES.txt
dupfinder.egg-info/dependency_links.txt
dupfinder.egg-info/entry_points.txt
dupfinder.egg-info/namespace_packages.txt
dupfinder.egg-info/not-zip-safe
dupfinder.egg-info/requires.txt
dupfinder.egg-info/top_level.txt