Metadata-Version: 1.0
Name: dupfinder
Version: 1.4.3
Summary: Find and manage duplication files on the file system
Home-page: http://python.org/pypi/dupfinder
Author: Andriy Mylenkyy
Author-email: mylanium@gmail.com
License: GPL
Keywords: file duplication finder manager
Platform: UNKNOWN
